XTransferBench/__init__.py
XTransferBench/attacker/__init__.py
XTransferBench/attacker/advclip.py
XTransferBench/attacker/xtransfer.py
XTransferBench/zoo/__init__.py
XTransferBench/zoo/collections/__init__.py
XTransferBench/zoo/collections/advclip.json
XTransferBench/zoo/collections/l2_non_targeted.json
XTransferBench/zoo/collections/l2_targeted.json
XTransferBench/zoo/collections/linf_non_targeted.json
XTransferBench/zoo/collections/linf_targeted.json
xtransferbench-0.1.2.dist-info/licenses/LICENSE
xtransferbench-0.1.2.dist-info/METADATA
xtransferbench-0.1.2.dist-info/WHEEL
xtransferbench-0.1.2.dist-info/top_level.txt
xtransferbench-0.1.2.dist-info/RECORD
