Metadata-Version: 2.4
Name: XTransferBench
Version: 0.1.2
Summary: This package provides UAPs for robustness evaluation.
Author-email: Hanxun Huang <hanxun@unimelb.edu.au>
Maintainer-email: Hanxun Huang <hanxun@unimelb.edu.au>
Project-URL: Homepage, https://github.com/HanxunH/XTransferBench
Project-URL: Bug Reports, https://github.com/HanxunH/XTransferBench
Project-URL: Funding, https://github.com/HanxunH/XTransferBench
Project-URL: Say Thanks!, https://github.com/HanxunH/XTransferBench
Project-URL: Source, https://github.com/HanxunH/XTransferBench
Keywords: XTransfer,UAP,Robustness,Adversarial
Classifier: Development Status :: 3 - Alpha
Classifier: Intended Audience :: Developers
Classifier: Topic :: Software Development :: Build Tools
Classifier: License :: OSI Approved :: MIT License
Classifier: Programming Language :: Python :: 3
Classifier: Programming Language :: Python :: 3.9
Classifier: Programming Language :: Python :: 3.10
Classifier: Programming Language :: Python :: 3.11
Classifier: Programming Language :: Python :: 3.12
Classifier: Programming Language :: Python :: 3.13
Classifier: Programming Language :: Python :: 3 :: Only
Requires-Python: >=3.0
License-File: LICENSE
Requires-Dist: torch
Requires-Dist: torchvision
Requires-Dist: huggingface-hub
Provides-Extra: dev
Requires-Dist: check-manifest; extra == "dev"
Provides-Extra: test
Requires-Dist: coverage; extra == "test"
Dynamic: license-file
